freeway/__init__.py
freeway/errors.cp39-win_amd64.pyd
freeway/errors.py
freeway/freeway.cp39-win_amd64.pyd
freeway/freeway.py
freeway/versioner.cp39-win_amd64.pyd
freeway/versioner.py
freeway-0.0.12.dist-info/LICENSE
freeway-0.0.12.dist-info/METADATA
freeway-0.0.12.dist-info/WHEEL
freeway-0.0.12.dist-info/top_level.txt
freeway-0.0.12.dist-info/RECORD
