Metadata-Version: 2.1
Name: freeway
Version: 0.0.12
Summary: Freeway is a module for managing file system structures with recursive pattern rules.
Home-page: https://github.com/cesioarg
Author: Leandro Inocencio
Author-email: cesio.arg@gmail.com
License: MIT
Download-URL: https://github.com/cesioarg/freeway/archive/v0.0.12.tar.gz
Keywords: filesystem,pipeline,parser,folders,patterns
Platform: UNKNOWN
Classifier: Development Status :: 3 - Alpha
Classifier: Natural Language :: Spanish
Classifier: Programming Language :: Python :: 3.7
Classifier: Topic :: System :: Filesystems
Classifier: License :: OSI Approved :: MIT License
Classifier: Operating System :: OS Independent
Requires-Dist: cython
Provides-Extra: dev
Requires-Dist: pytest (>=3.7) ; extra == 'dev'
